sensirion_ble/__init__.py
sensirion_ble/const.py
sensirion_ble/converters.py
sensirion_ble/parser.py
sensirion_ble/py.typed
sensirion_ble/types.py
sensirion_ble-0.1.1.dist-info/METADATA
sensirion_ble-0.1.1.dist-info/WHEEL
sensirion_ble-0.1.1.dist-info/licenses/LICENSE
sensirion_ble-0.1.1.dist-info/RECORD
